LICENSE
MANIFEST.in
README.md
requirements.txt
setup.py
fullmonte/__init__.py
fullmonte/plot.py
fullmonte/simulation.py
fullmonte.egg-info/PKG-INFO
fullmonte.egg-info/SOURCES.txt
fullmonte.egg-info/dependency_links.txt
fullmonte.egg-info/not-zip-safe
fullmonte.egg-info/requires.txt
fullmonte.egg-info/top_level.txt