Metadata-Version: 2.1
Name: fullmonte
Version: 0.0.2
Summary: A monte carlo simulation for extrapolated returns.
Home-page: https://github.com/8W9aG/fullmonte
Author: Will Sackfield
Author-email: will.sackfield@gmail.com
License: MIT
Keywords: monte carlo
Classifier: License :: OSI Approved :: MIT License
Classifier: Programming Language :: Python :: 3
License-File: LICENSE
Requires-Dist: pandas>=2.2.1
Requires-Dist: numpy>=1.26.0
Requires-Dist: matplotlib>=3.8.3
